COPYRIGHT.txt
LICENSE.txt
MANIFEST.in
README.rst
README.txt
SUDS_ADJUNCT_LICENSE.txt
SUDS_LICENSE.txt
setup.py
doc/SudsLibrary.html
src/ez_setup.py
src/SudsLibrary/__init__.py
src/SudsLibrary/clientmanagement.py
src/SudsLibrary/factory.py
src/SudsLibrary/monkeypatches.py
src/SudsLibrary/options.py
src/SudsLibrary/proxy.py
src/SudsLibrary/soaplogging.py
src/SudsLibrary/utils.py
src/SudsLibrary/version.py
src/SudsLibrary/wsse.py
src/robotframework_sudslibrary.egg-info/PKG-INFO
src/robotframework_sudslibrary.egg-info/SOURCES.txt
src/robotframework_sudslibrary.egg-info/dependency_links.txt
src/robotframework_sudslibrary.egg-info/requires.txt
src/robotframework_sudslibrary.egg-info/top_level.txt
src/robotframework_sudslibrary.egg-info/zip-safe
test/testenv.py