Metadata-Version: 1.1
Name: robotframework-sudslibrary
Version: 0.8
Summary: Robot Framework test library for SOAP-based services.
Home-page: https://github.com/ombre42/robotframework-sudslibrary
Author: Kevin Ormbrek
Author-email: <kormbrek@gmail.com>
License: Apache License 2.0
Keywords: robotframework testing testautomation soap suds web service
Platform: any
Classifier: Development Status :: 5 - Production/Stable
Classifier: License :: OSI Approved :: Apache Software License
Classifier: Operating System :: OS Independent
Classifier: Programming Language :: Python
Classifier: Topic :: Software Development :: Testing
